gpio_device/__init__.py
gpio_device/gpio_device.py
pi_gpio_device-0.1.dist-info/LICENSE
pi_gpio_device-0.1.dist-info/METADATA
pi_gpio_device-0.1.dist-info/WHEEL
pi_gpio_device-0.1.dist-info/top_level.txt
pi_gpio_device-0.1.dist-info/RECORD
