Metadata-Version: 2.1
Name: pi_gpio_device
Version: 0.1
Summary: GPIO control
Home-page: https://github.com/neudeeptech/Pi-GpioControl.git
Author: Komal Swami
Author-email: komalsswami@example.com
License: Custom License
Classifier: Programming Language :: Python :: 3
Classifier: License :: OSI Approved :: MIT License
Classifier: Operating System :: OS Independent
Requires-Python: >=3.10
License-File: LICENSE
Requires-Dist: RPi.GPIO
